umaapy/__init__.py
umaapy/_version.py
umaapy/umaa_types.py
umaapy/core/__init__.py
umaapy/core/command_consumer.py
umaapy/core/command_provider.py
umaapy/core/report_consumer.py
umaapy/core/report_provider.py
umaapy/examples/__init__.py
umaapy/examples/global_vector_control.py
umaapy/resource/__init__.py
umaapy/resource/umaapy_qos_lib.xml
umaapy/util/__init__.py
umaapy/util/command_session.py
umaapy/util/dds_configurator.py
umaapy/util/event_processor.py
umaapy/util/multi_topic_reader.py
umaapy/util/multi_topic_reader_decorators.py
umaapy/util/multi_topic_support.py
umaapy/util/multi_topic_writer.py
umaapy/util/multi_topic_writer_decorators.py
umaapy/util/provider.py
umaapy/util/reader_listener.py
umaapy/util/timestamp.py
umaapy/util/umaa_command.py
umaapy/util/umaa_utils.py
umaapy/util/uuid_factory.py
umaapy-1.1.1.dist-info/licenses/LICENSE
umaapy-1.1.1.dist-info/METADATA
umaapy-1.1.1.dist-info/WHEEL
umaapy-1.1.1.dist-info/top_level.txt
umaapy-1.1.1.dist-info/RECORD
