Metadata-Version: 2.4
Name: umaapy
Version: 1.1.1
Summary: Python UMAA SDK for rapid autonomy development
Author-email: Devon Reed <clr5436@psu.edu>
Project-URL: Homepage, https://github.com/dkreed747/umaapy
Project-URL: Repository, https://github.com/dkreed747/umaapy
Project-URL: Issues, https://github.com/dkreed747/umaapy/issues
Project-URL: Documentation, https://dkreed747.github.io/umaapy/
Classifier: Programming Language :: Python :: 3
Classifier: License :: OSI Approved :: MIT License
Classifier: Operating System :: OS Independent
Requires-Python: >=3.13
License-File: LICENSE
Requires-Dist: rti.connext>=7.5.0
Provides-Extra: tests
Requires-Dist: pytest>=8.4.1; extra == "tests"
Requires-Dist: pytest-cov>=6.2.1; extra == "tests"
Provides-Extra: docs
Requires-Dist: Sphinx>=8.2.3; extra == "docs"
Requires-Dist: sphinx-autodoc-typehints>=3.2.0; extra == "docs"
Requires-Dist: autodocsumm>=0.2.14; extra == "docs"
Requires-Dist: sphinx_rtd_theme>=3.0.2; extra == "docs"
Requires-Dist: doc8>=2.0.0; extra == "docs"
Requires-Dist: sphinxcontrib-mermaid>=1.0.0; extra == "docs"
Requires-Dist: rstcheck>=6.2.5; extra == "docs"
Dynamic: license-file
